nonebot/adapters/minecraft/__init__.py
nonebot/adapters/minecraft/adapter.py
nonebot/adapters/minecraft/bot.py
nonebot/adapters/minecraft/collator.py
nonebot/adapters/minecraft/compat.py
nonebot/adapters/minecraft/config.py
nonebot/adapters/minecraft/event.py
nonebot/adapters/minecraft/exception.py
nonebot/adapters/minecraft/message.py
nonebot/adapters/minecraft/models.py
nonebot/adapters/minecraft/permission.py
nonebot/adapters/minecraft/store.py
nonebot/adapters/minecraft/utils.py
nonebot_adapter_minecraft-1.7.1.dist-info/METADATA
nonebot_adapter_minecraft-1.7.1.dist-info/WHEEL
nonebot_adapter_minecraft-1.7.1.dist-info/licenses/LICENSE
nonebot_adapter_minecraft-1.7.1.dist-info/RECORD
