Metadata-Version: 2.4
Name: nonebot-adapter-minecraft
Version: 1.7.1
Summary: NoneBot2与MineCraft Server互通的适配器。
Author-email: 17TheWord <17theword@gmail.com>
License-Expression: MIT
License-File: LICENSE
Requires-Python: <4.0,>=3.10
Requires-Dist: nonebot2[fastapi,httpx,websockets]<3,>=2.2.0
Requires-Dist: pydantic!=2.5.0,!=2.5.1,<3.0.0,>=1.10.0
